conscompf/__init__.py
conscompf/conscompf.py
conscompf-0.2.dist-info/METADATA
conscompf-0.2.dist-info/WHEEL
conscompf-0.2.dist-info/licenses/LICENSE
conscompf-0.2.dist-info/RECORD
