Metadata-Version: 2.4
Name: conscompf
Version: 0.2
Summary: Consistency-focused similarity comparison framework for generative large language models
Project-URL: Homepage, https://github.com/alex-karev/conscompf
Project-URL: Issues, https://github.com/alex-karev/conscompf/issues
Author-email: Alex Karev <karev.as99@gmail.com>
License-File: LICENSE
Classifier: Operating System :: OS Independent
Classifier: Programming Language :: Python :: 3
Requires-Python: >=3.10
